{"advanced_optional-cfg-1.md":"4885cb35","advanced_power-ctl.md":"dedf363b","advanced_beauty-3.md":"92ebe90c","advanced_btrfs.md":"b4bee558","advanced_system-ctl.md":"339eb246","apps_collaboration.md":"54c03de3","advanced_beauty-1.md":"f4ab70ed","apps_remote.md":"cb23ba75","apps_communication.md":"5e270171","apps_daily.md":"b282b673","apps_office.md":"a50eb580","apps_media.md":"fc259b62","apps_android.md":"e807e8ed","advanced_debug.md":"b1fa6507","advanced_beauty-2.md":"cca0e72e","apps_play.md":"f6fe3c99","advanced_make-install-disk.md":"caedd9e4","advanced_optional-cfg-2.md":"dea7dc84","exclusive_code.md":"6556f157","exclusive_audio.md":"3edb3126","postscript_about.md":"256fa93c","postscript_contribute.md":"f50f1b2f","prepare_head-on-blow.md":"17b0c37c","exclusive_image.md":"5aab381a","postscript_postscript.md":"f14f0e10","prologue.md":"3a7c4e44","postscript_contributor-covenant.md":"45a81ef2","index.md":"d089fad8","postscript_copyright.md":"9c412105","prepare_understand.md":"cf6509e1","rookie_graphic-driver.md":"f3f1a572","rookie_basic-install.md":"5847339a","rookie_transparent.md":"dbfc3285","rookie_pre-install.md":"c556922d","exclusive_media.md":"872a2c32","exclusive_vedio.md":"9d8d13d9","rookie_pre-virt.md":"82e06867","rookie_desktop-env-and-app.md":"a0966821","rookie_basic-install-detail.md":"e148d20b"}
